flask_oso/__init__.py
flask_oso/context.py
flask_oso/decorators.py
flask_oso/flask_oso.py
flask_oso-0.27.0.dist-info/METADATA
flask_oso-0.27.0.dist-info/WHEEL
flask_oso-0.27.0.dist-info/entry_points.txt
flask_oso-0.27.0.dist-info/top_level.txt
flask_oso-0.27.0.dist-info/RECORD
