Metadata-Version: 2.1
Name: flask-oso
Version: 0.27.0
Summary: oso flask integration
Home-page: UNKNOWN
Author: Oso Security, Inc.
License: UNKNOWN
Platform: UNKNOWN
Classifier: Development Status :: 4 - Beta
Classifier: Programming Language :: Python :: 3.7
Classifier: License :: OSI Approved :: Apache Software License
Requires-Python: >=3.7
Requires-Dist: oso (~=0.27.0)
Requires-Dist: flask (==2.1.0)
Requires-Dist: werkzeug (==2.0.3)
